_ForestDiffusion/README.MD
_ForestDiffusion/__init__.py
_ForestDiffusion/diffusion_with_trees_class.py
_ForestDiffusion/utils/__init__.py
_ForestDiffusion/utils/diffusion.py
_ForestDiffusion/utils/utils_diffusion.py
_ctgan/README.MD
_ctgan/__init__.py
_ctgan/conditional.py
_ctgan/models.py
_ctgan/sampler.py
_ctgan/synthesizer.py
_ctgan/transformer.py
tabgan/__init__.py
tabgan/abc_sampler.py
tabgan/adversarial_model.py
tabgan/encoders.py
tabgan/sampler.py
tabgan/utils.py
tabgan-2.2.4.dist-info/AUTHORS.rst
tabgan-2.2.4.dist-info/LICENSE
tabgan-2.2.4.dist-info/METADATA
tabgan-2.2.4.dist-info/WHEEL
tabgan-2.2.4.dist-info/top_level.txt
tabgan-2.2.4.dist-info/RECORD
