Metadata-Version: 2.1
Name: tabgan
Version: 2.2.4
Summary: Applying GAN in tabular data generation for uneven distribution
Home-page: https://github.com/Diyago/GAN-for-tabular-data
Author: Insaf Ashrapov
Author-email: iashrapov@gmail.com
License: Apache License 2.0
Project-URL: Documentation, https://github.com/Diyago/GAN-for-tabular-data
Platform: any
Classifier: Development Status :: 5 - Production/Stable
Classifier: Programming Language :: Python
Requires-Python: >=3.5
License-File: LICENSE
License-File: AUTHORS.rst
Requires-Dist: pandas
Requires-Dist: numpy (>=2.0)
Requires-Dist: category-encoders
Requires-Dist: torch (>=1.0)
Requires-Dist: lightgbm (>=2.2.3)
Requires-Dist: scikit-learn (>=1.5.2)
Requires-Dist: torchvision
Requires-Dist: python-dateutil
Requires-Dist: tqdm
Requires-Dist: xgboost
Requires-Dist: be-great
Provides-Extra: testing
Requires-Dist: pytest ; extra == 'testing'
Requires-Dist: pytest-cov ; extra == 'testing'
